pacxplorerng/__init__.py
pacxplorerng/coordinator.py
pacxplorerng/definitions.py
pacxplorerng/explorer.py
pacxplorerng/ida_plugin.py
pacxplorerng/analyzers/__init__.py
pacxplorerng/analyzers/movk.py
pacxplorerng/analyzers/vtable.py
pacxplorerng/gui/__init__.py
pacxplorerng/gui/actions.py
pacxplorerng/gui/choose.py
pacxplorerng/storage/__init__.py
pacxplorerng/storage/netnodes.py
pacxplorer_ng-1.0.2.dist-info/METADATA
pacxplorer_ng-1.0.2.dist-info/WHEEL
pacxplorer_ng-1.0.2.dist-info/licenses/LICENSE.txt
pacxplorer_ng-1.0.2.dist-info/RECORD
