Metadata-Version: 2.4
Name: pacxplorer-ng
Version: 1.0.2
Summary: IDA Plugin that adds XREFs between virtual functions and their call sites
Project-URL: Homepage, https://github.com/yoavst/pacxplorer-ng
Project-URL: Issues, https://github.com/yoavst/pacxplorer-ng/issues
Author-email: Yoav Sternberg <yoav.sternberg@gmail.com>
License-File: LICENSE.txt
Classifier: License :: OSI Approved :: GNU General Public License v3 (GPLv3)
Classifier: Operating System :: OS Independent
Classifier: Programming Language :: Python :: 3
Requires-Python: >=3.10
Requires-Dist: capstone==6.0.0a5
Requires-Dist: ida-netnode>=3.0
